[{"#Type Icon":"","Browseable":true,"DisplayName":"1990","Formatted Name":"Physical Therapists","HierarchyPosition":"BINGL00003000040000B0000100001000080000O00001","Id":"592144659","LevelNumber":9,"NamePath":"[Application]\\\\Structure\\\\Content\\\\Categories\\\\Business\\\\Master\\\\11384\\\\11683\\\\1990","NodeLastUpdate":"40562.4254743827","ObjectType":"Business","ObjectTypeName":"Business","PointerType":"O","Previewable":false,"PrimaryObjectTypePosition":"BINGL00001000010000G0000100001","Rank":1,"Selectable":true,"SubNodeCount":0,"__TOTALITEMS__":4},
{"#Type Icon":"","Browseable":true,"DisplayName":"1991","Formatted Name":"Physical Therapists Equipment","HierarchyPosition":"BINGL00003000040000B0000100001000080000O00002","Id":"592144663","LevelNumber":9,"NamePath":"[Application]\\\\Structure\\\\Content\\\\Categories\\\\Business\\\\Master\\\\11384\\\\11683\\\\1991","NodeLastUpdate":"40562.425477392","ObjectType":"Business","ObjectTypeName":"Business","PointerType":"O","Previewable":false,"PrimaryObjectTypePosition":"BINGL00001000010000G0000100001","Rank":2,"Selectable":true,"SubNodeCount":0},
{"#Type Icon":"","Browseable":true,"DisplayName":"2025","Formatted Name":"Physical Medicine &amp; Rehabilitation Specialists","HierarchyPosition":"BINGL00003000040000B0000100001000080000O00003","Id":"592144665","LevelNumber":9,"NamePath":"[Application]\\\\Structure\\\\Content\\\\Categories\\\\Business\\\\Master\\\\11384\\\\11683\\\\2025","NodeLastUpdate":"40562.4254797454","ObjectType":"Business","ObjectTypeName":"Business","PointerType":"O","Previewable":false,"PrimaryObjectTypePosition":"BINGL00001000010000G0000100001","Rank":3,"Selectable":true,"SubNodeCount":0},
{"#Type Icon":"","Browseable":true,"DisplayName":"2258","Formatted Name":"Rehabilitation Services","HierarchyPosition":"BINGL00003000040000B0000100001000080000O00004","Id":"592144670","LevelNumber":9,"NamePath":"[Application]\\\\Structure\\\\Content\\\\Categories\\\\Business\\\\Master\\\\11384\\\\11683\\\\2258","NodeLastUpdate":"40562.4254835648","ObjectType":"Business","ObjectTypeName":"Business","PointerType":"O","Previewable":false,"PrimaryObjectTypePosition":"BINGL00001000010000G0000100001","Rank":4,"Selectable":true,"SubNodeCount":0}]
