[{"#Type Icon":"","Browseable":true,"DisplayName":"435","Formatted Name":"Burglar Alarm Systems","HierarchyPosition":"BINGL00003000040000B00001000010000C0000N00001","Id":"592145814","LevelNumber":9,"NamePath":"[Application]\\\\Structure\\\\Content\\\\Categories\\\\Business\\\\Master\\\\12360\\\\13497\\\\435","NodeLastUpdate":"40562.4282497299","ObjectType":"Business","ObjectTypeName":"Business","PointerType":"O","Previewable":false,"PrimaryObjectTypePosition":"BINGL00001000010000G0000100001","Rank":1,"Selectable":true,"SubNodeCount":0,"__TOTALITEMS__":12},
{"#Type Icon":"","Browseable":true,"DisplayName":"906","Formatted Name":"Earthquake Products &amp; Services","HierarchyPosition":"BINGL00003000040000B00001000010000C0000N00002","Id":"592145815","LevelNumber":9,"NamePath":"[Application]\\\\Structure\\\\Content\\\\Categories\\\\Business\\\\Master\\\\12360\\\\13497\\\\906","NodeLastUpdate":"40562.4282560571","ObjectType":"Business","ObjectTypeName":"Business","PointerType":"O","Previewable":false,"PrimaryObjectTypePosition":"BINGL00001000010000G0000100001","Rank":2,"Selectable":true,"SubNodeCount":0},
{"#Type Icon":"","Browseable":true,"DisplayName":"1052","Formatted Name":"Fire Alarm Systems","HierarchyPosition":"BINGL00003000040000B00001000010000C0000N00003","Id":"592145816","LevelNumber":9,"NamePath":"[Application]\\\\Structure\\\\Content\\\\Categories\\\\Business\\\\Master\\\\12360\\\\13497\\\\1052","NodeLastUpdate":"40562.4282637731","ObjectType":"Business","ObjectTypeName":"Business","PointerType":"O","Previewable":false,"PrimaryObjectTypePosition":"BINGL00001000010000G0000100001","Rank":3,"Selectable":true,"SubNodeCount":0},
{"#Type Icon":"","Browseable":true,"DisplayName":"1055","Formatted Name":"Fire Protection Consultants &amp; Services","HierarchyPosition":"BINGL00003000040000B00001000010000C0000N00004","Id":"592145817","LevelNumber":9,"NamePath":"[Application]\\\\Structure\\\\Content\\\\Categories\\\\Business\\\\Master\\\\12360\\\\13497\\\\1055","NodeLastUpdate":"40562.4282677855","ObjectType":"Business","ObjectTypeName":"Business","PointerType":"O","Previewable":false,"PrimaryObjectTypePosition":"BINGL00001000010000G0000100001","Rank":4,"Selectable":true,"SubNodeCount":0},
{"#Type Icon":"","Browseable":true,"DisplayName":"1056","Formatted Name":"Fire Protection Equipment &amp; Supplies","HierarchyPosition":"BINGL00003000040000B00001000010000C0000N00005","Id":"592145818","LevelNumber":9,"NamePath":"[Application]\\\\Structure\\\\Content\\\\Categories\\\\Business\\\\Master\\\\12360\\\\13497\\\\1056","NodeLastUpdate":"40562.4282714892","ObjectType":"Business","ObjectTypeName":"Business","PointerType":"O","Previewable":false,"PrimaryObjectTypePosition":"BINGL00001000010000G0000100001","Rank":5,"Selectable":true,"SubNodeCount":0},
{"#Type Icon":"","Browseable":true,"DisplayName":"1061","Formatted Name":"Fireproofing &amp; Firestopping","HierarchyPosition":"BINGL00003000040000B00001000010000C0000N00006","Id":"592145819","LevelNumber":9,"NamePath":"[Application]\\\\Structure\\\\Content\\\\Categories\\\\Business\\\\Master\\\\12360\\\\13497\\\\1061","NodeLastUpdate":"40562.428275","ObjectType":"Business","ObjectTypeName":"Business","PointerType":"O","Previewable":false,"PrimaryObjectTypePosition":"BINGL00001000010000G0000100001","Rank":6,"Selectable":true,"SubNodeCount":0},
{"#Type Icon":"","Browseable":true,"DisplayName":"1323","Formatted Name":"Home Automation Systems &amp; Services","HierarchyPosition":"BINGL00003000040000B00001000010000C0000N00007","Id":"592145820","LevelNumber":9,"NamePath":"[Application]\\\\Structure\\\\Content\\\\Categories\\\\Business\\\\Master\\\\12360\\\\13497\\\\1323","NodeLastUpdate":"40562.4282799769","ObjectType":"Business","ObjectTypeName":"Business","PointerType":"O","Previewable":false,"PrimaryObjectTypePosition":"BINGL00001000010000G0000100001","Rank":7,"Selectable":true,"SubNodeCount":0},
{"#Type Icon":"","Browseable":true,"DisplayName":"1554","Formatted Name":"Lightning Protection Equipment","HierarchyPosition":"BINGL00003000040000B00001000010000C0000N00008","Id":"592145821","LevelNumber":9,"NamePath":"[Application]\\\\Structure\\\\Content\\\\Categories\\\\Business\\\\Master\\\\12360\\\\13497\\\\1554","NodeLastUpdate":"40562.428284375","ObjectType":"Business","ObjectTypeName":"Business","PointerType":"O","Previewable":false,"PrimaryObjectTypePosition":"BINGL00001000010000G0000100001","Rank":8,"Selectable":true,"SubNodeCount":0},
{"#Type Icon":"","Browseable":true,"DisplayName":"2324","Formatted Name":"Safety Equipment","HierarchyPosition":"BINGL00003000040000B00001000010000C0000N00009","Id":"592145822","LevelNumber":9,"NamePath":"[Application]\\\\Structure\\\\Content\\\\Categories\\\\Business\\\\Master\\\\12360\\\\13497\\\\2324","NodeLastUpdate":"40562.4282883102","ObjectType":"Business","ObjectTypeName":"Business","PointerType":"O","Previewable":false,"PrimaryObjectTypePosition":"BINGL00001000010000G0000100001","Rank":9,"Selectable":true,"SubNodeCount":0},
{"#Type Icon":"","Browseable":true,"DisplayName":"2506","Formatted Name":"Automatic Fire Sprinklers","HierarchyPosition":"BINGL00003000040000B00001000010000C0000N0000A","Id":"592145823","LevelNumber":9,"NamePath":"[Application]\\\\Structure\\\\Content\\\\Categories\\\\Business\\\\Master\\\\12360\\\\13497\\\\2506","NodeLastUpdate":"40562.4282903935","ObjectType":"Business","ObjectTypeName":"Business","PointerType":"O","Previewable":false,"PrimaryObjectTypePosition":"BINGL00001000010000G0000100001","Rank":10,"Selectable":true,"SubNodeCount":0},
{"#Type Icon":"","Browseable":true,"DisplayName":"12473","Formatted Name":"Disaster Protection Services","HierarchyPosition":"BINGL00003000040000B00001000010000C0000N0000B","Id":"592145824","LevelNumber":9,"NamePath":"[Application]\\\\Structure\\\\Content\\\\Categories\\\\Business\\\\Master\\\\12360\\\\13497\\\\12473","NodeLastUpdate":"40562.4282929398","ObjectType":"Business","ObjectTypeName":"Business","PointerType":"O","Previewable":false,"PrimaryObjectTypePosition":"BINGL00001000010000G0000100001","Rank":11,"Selectable":true,"SubNodeCount":0},
{"#Type Icon":"","Browseable":true,"DisplayName":"13539","Formatted Name":"Searchlights &amp; Floodlights","HierarchyPosition":"BINGL00003000040000B00001000010000C0000N0000C","Id":"592145825","LevelNumber":9,"NamePath":"[Application]\\\\Structure\\\\Content\\\\Categories\\\\Business\\\\Master\\\\12360\\\\13497\\\\13539","NodeLastUpdate":"40562.4282951003","ObjectType":"Business","ObjectTypeName":"Business","PointerType":"O","Previewable":false,"PrimaryObjectTypePosition":"BINGL00001000010000G0000100001","Rank":12,"Selectable":true,"SubNodeCount":0}]
